dragonfly_comparison/__init__.py
dragonfly_comparison/_extend_dragonfly.py
dragonfly_comparison/properties/__init__.py
dragonfly_comparison/properties/model.py
dragonfly_comparison/properties/room2d.py
dragonfly_comparison-0.1.7.dist-info/licenses/LICENSE
dragonfly_comparison-0.1.7.dist-info/METADATA
dragonfly_comparison-0.1.7.dist-info/WHEEL
dragonfly_comparison-0.1.7.dist-info/top_level.txt
dragonfly_comparison-0.1.7.dist-info/RECORD
